{
  "resturents": [
    {
      "name": "Usama",
      "email": "usamakhalied@gmail.com",
      "address": "Tariq Road",
      "department": "",
      "education": "Inter",
      "fathername": "Khalied Mehmood",
      "hobies": "Editting",
      "telephoneNo": "9292929292",
      "Skills": "",
      "gender": "male",
      "id": 1
    }
  ],
  "users": [
    {
      "name": "wfcedcf",
      "email": "wfcedcf",
      "password": "dsdaddad",
      "id": 1
    },
    {
      "name": "Muhammad Usama khalied",
      "email": "usamakhalied@gmail.com",
      "password": "12231",
      "id": 2
    },
    {
      "name": "Usama",
      "email": "Anus",
      "password": "sdada",
      "id": 3
    },
    {
      "name": "usama",
      "email": "usama",
      "password": "trertre",
      "id": 4
    }
  ]
}